{
  "Atmosphere (Official Music Video)": {
    "Artist Name": "Rhea Raj",
    "Link": "https://www.youtube.com/embed/MQA19QErKqk"
  },
  "Either Way (Official Lyric Video)": {
    "Artist Name": "LYRIC",
    "Link": "https://www.youtube.com/embed/XtukBGVA61c"
  },
  "Madame Ponsardin (Official Music Video)": {
    "Artist Name": "Dúse Saida",
    "Link": "https://www.youtube.com/embed/hmZAXNdO6Io"
  },
  "Call Ya Bluff": {
    "Artist Name": "La2Us",
    "Link": "https://www.youtube.com/embed/5yxkCJJ0-aE"
  },
  "Atmosphere (Lyric Video)": {
    "Artist Name": "Rhea Raj",
    "Link": "https://www.youtube.com/embed/09ez7kZ8k8Q"
  },
  "First Impression Freestyle": {
    "Artist Name": "LaChaleur",
    "Link": "https://www.youtube.com/embed/EHHQ6BJHgJI"
  },
  "Atmosphere (Orchestral Remix)": {
    "Artist Name": "Rhea Raj",
    "Link": "https://www.youtube.com/embed/VLNsNQ9sYM0"
  }
}
